render_thumbnail/.main.py.swp
render_thumbnail/__init__.py
render_thumbnail/__main__.py
render_thumbnail/functions_tex.py
render_thumbnail/main.py
render_thumbnail-0.1.22.dist-info/METADATA
render_thumbnail-0.1.22.dist-info/WHEEL
render_thumbnail-0.1.22.dist-info/entry_points.txt
render_thumbnail-0.1.22.dist-info/RECORD
