Metadata-Version: 2.1
Name: render-thumbnail
Version: 0.1.22
Summary: Fixed extracting functions for year as well as exam
Author: vaibhavblayer
Author-email: vaibhavblayer@gmail.com
Requires-Python: >=3.11,<4.0
Classifier: Programming Language :: Python :: 3
Classifier: Programming Language :: Python :: 3.11
